PandasColorPrinter/README.MD
PandasColorPrinter/__init__.py
PandasColorPrinter/requirements.txt
PandasColorPrinter/thirdparty.json
PandasColorPrinter-0.45.dist-info/LICENSE.rst
PandasColorPrinter-0.45.dist-info/METADATA
PandasColorPrinter-0.45.dist-info/WHEEL
PandasColorPrinter-0.45.dist-info/top_level.txt
PandasColorPrinter-0.45.dist-info/RECORD
