Metadata-Version: 2.1
Name: PandasColorPrinter
Version: 0.45
Summary: Pandas DataFrames / Pandas Series / Print colored Numpy arrays / lists / dicts / tuples!
Home-page: https://github.com/hansalemaos/PandasColorPrinter
Author: Johannes Fischer
Author-email: aulasparticularesdealemaosp@gmail.com
License: MIT
Keywords: pandas,numpy,dataframe,series,print,prettyprint,colored,coloured
Classifier: Development Status :: 4 - Beta
Classifier: Programming Language :: Python :: 3 :: Only
Classifier: Programming Language :: Python :: 3.10
Classifier: Topic :: Software Development :: Libraries :: Python Modules
Classifier: Topic :: Utilities
License-File: LICENSE.rst
Requires-Dist: cprinter
Requires-Dist: input-timeout
Requires-Dist: keyboard
Requires-Dist: kthread
Requires-Dist: numpy
Requires-Dist: pandas
Requires-Dist: regex
